MANIFEST.in
README
setup.py
dishes/__init__.py
dishes/admin.py
dishes/api.py
dishes/forms.py
dishes/managers.py
dishes/models.py
dishes/urls.py
dishes/templatetags/__init__.py
dishes/templatetags/dishes_filters.py
dishes/templatetags/dishes_tags.py
dishes/utils/__init__.py
dishes/utils/units.py
django_dishes.egg-info/PKG-INFO
django_dishes.egg-info/SOURCES.txt
django_dishes.egg-info/dependency_links.txt
django_dishes.egg-info/top_level.txt
django_dishes.egg-info/zip-safe