Metadata-Version: 1.0
Name: django-dishes
Version: 0.1.1
Summary: We need menus of delicious food that people can order and have delivered.
Home-page: http://github.com/powellc/django-dishes
Author: Colin Powell
Author-email: colin@onecardinal.com
License: BSD
Download-URL: http://github.com/powellc/django-dishes/downloads
Platform: UNKNOWN
Classifier: Development Status :: 4 - Beta
Classifier: Environment :: Web Environment
Classifier: Intended Audience :: Developers
Classifier: License :: OSI Approved :: BSD License
Classifier: Operating System :: OS Independent
Classifier: Programming Language :: Python
Classifier: Framework :: Django
